MANIFEST.in
README.md
__version__.txt
setup.cfg
setup.py
mutamorphic_test.egg-info/PKG-INFO
mutamorphic_test.egg-info/SOURCES.txt
mutamorphic_test.egg-info/dependency_links.txt
mutamorphic_test.egg-info/requires.txt
mutamorphic_test.egg-info/top_level.txt
mutatest/Word.py
mutatest/__init__.py
mutatest/dropout_mutator.py
mutatest/mutators.py
mutatest/replacement_mutator.py
mutatest/test_runner.py