Metadata-Version: 2.1
Name: mutamorphic-test
Version: 0.0.3
Summary: Mutamorhpic testing tool for text-based machine learning problems.
Home-page: https://github.com/Maarten0110/mutatest
Author: Maarten van Tartwijk
Author-email: m.j.vantartwijk@student.tudelft.nl
License: UNKNOWN
Project-URL: Source, https://github.com/Maarten0110/mutatest
Keywords: machine learning testing mutamorphic
Platform: UNKNOWN
Requires-Python: >=3.7
